CHANGELOG.md
LICENSE
cloudmage/gitutils/__init__.py
cloudmage/gitutils/gitconfig_parser.py
cloudmage/gitutils/github_reports.py
cloudmage/gitutils/templates/Github_Open_PR_Report.j2
cloudmage_gitutils-1.0.2.dist-info/LICENSE
cloudmage_gitutils-1.0.2.dist-info/METADATA
cloudmage_gitutils-1.0.2.dist-info/WHEEL
cloudmage_gitutils-1.0.2.dist-info/entry_points.txt
cloudmage_gitutils-1.0.2.dist-info/RECORD
