Metadata-Version: 2.1
Name: cloudmage-gitutils
Version: 1.0.2
Summary: Git based helpers and Report Templates
Home-page: https://github.com/CloudMaege/PYPKG-GitUtils.git
License: GPL-3.0-or-later
Keywords: Packages,CloudMage,CloudMaege,CloudMæge,Git
Author: Rich Nason
Author-email: rnason@cloudmage.io
Maintainer: Rich Naeson
Maintainer-email: cloudmaege@naeson.nl
Requires-Python: >=3.10,<4.0
Classifier: Environment :: Console
Classifier: License :: OSI Approved :: GNU General Public License v3 or later (GPLv3+)
Classifier: Operating System :: OS Independent
Classifier: Programming Language :: Python :: 3
Classifier: Programming Language :: Python :: 3.10
Classifier: Programming Language :: Python :: 3.11
Classifier: Topic :: Software Development :: Documentation
Classifier: Topic :: Software Development :: Libraries :: Python Modules
Requires-Dist: PyGithub (>=2.1.1,<3.0.0)
Requires-Dist: cloudmage-jinjautils (>=1.0.7,<2.0.0)
Requires-Dist: progress (>=1.6,<2.0)
Requires-Dist: requests (>=2.31.0,<3.0.0)
Project-URL: Documentation, https://github.com/CloudMaege/PYPKG-GitUtils.git
Project-URL: Issues, https://github.com/CloudMaege/PYPKG-GitUtils/issues
Project-URL: Repository, https://github.com/CloudMaege/PYPKG-GitUtils.git
Project-URL: Releases, https://github.com/CloudMaege/PYPKG-GitUtils/releases
